HDL_example_41/sillyfunction.v
module sillyfunction(input a, b, c,
                     output y);

    assign y = ~a & ~b & ~c |
                a & ~b & ~c |
                a & ~b &  c;

endmodule

HDL_example_41/sillyfunction-test.v
module test;

    reg a;
    reg b;
    reg c;
    wire y;

    sillyfunction sf1(.a(a), .b(b), .c(c), .y(y));

    initial begin
        $dumpfile("sillyfunction-dump.vcd");
        $dumpvars(0, test);
        a = 0;
        b = 0;
        c = 0;
    #10 a = 0;
        b = 0;
        c = 1;
    #10 a = 0;
        b = 1;
        c = 0;
    #10 a = 0;
        b = 1;
        c = 1;
    #10 a = 1;
        b = 0;
        c = 0;
    #10 a = 1;
        b = 0;
        c = 1;
    #10 a = 1;
        b = 1;
        c = 0;
    #10 a = 1;
        b = 1;
        c = 1;
    #10 $finish;
    end
endmodule

HDL_example_41/sillyfunction-dump.vcd
$date
	Tue Dec  9 13:07:19 2014
$end
$version
	Icarus Verilog
$end
$timescale
	1s
$end
$scope module test $end
$var wire 1 ! y $end
$var reg 1 " a $end
$var reg 1 # b $end
$var reg 1 $ c $end
$scope module sf1 $end
$var wire 1 % a $end
$var wire 1 & b $end
$var wire 1 ' c $end
$var wire 1 ! y $end
$upscope $end
$upscope $end
$enddefinitions $end
#0
$dumpvars
0'
0&
0%
0$
0#
0"
1!
$end
#10
0!
1$
1'
#20
0$
0'
1#
1&
#30
1$
1'
#40
1!
0$
0'
0#
0&
1"
1%
#50
1$
1'
#60
0!
0$
0'
1#
1&
#70
1$
1'
